neodb/__init__.py
neodb/server.py
mseep_neodb_mcp-0.1.2.dist-info/METADATA
mseep_neodb_mcp-0.1.2.dist-info/WHEEL
mseep_neodb_mcp-0.1.2.dist-info/entry_points.txt
mseep_neodb_mcp-0.1.2.dist-info/licenses/LICENSE
mseep_neodb_mcp-0.1.2.dist-info/RECORD
