Metadata-Version: 2.4
Name: mseep-neodb-mcp
Version: 0.1.2
Summary: Add your description here
Author-email: mseep <support@skydeck.ai>
Maintainer-email: mseep <support@skydeck.ai>
License-File: LICENSE
Requires-Python: >=3.13
Requires-Dist: httpx>=0.28.1
Requires-Dist: mcp>=1.1.2
